Metadata-Version: 1.1
Name: nikepysdk
Version: 0.0.2
Summary: A Python3 SDK for interacting with Nike services
Home-page: https://github.com/kfichter/nike-py-sdk
Author: Kelvin Fichter
Author-email: kelvinfichter@gmail.com
License: MIT
Keywords: nike sneakers development
Platform: UNKNOWN
Classifier: Development Status :: 3 - Alpha
Classifier: Intended Audience :: Developers
Classifier: Topic :: Software Development :: Libraries :: Python Modules
Classifier: License :: OSI Approved :: MIT License
Classifier: Programming Language :: Python :: 2
Classifier: Programming Language :: Python :: 2.7
Classifier: Programming Language :: Python :: 3
Classifier: Programming Language :: Python :: 3.3
Classifier: Programming Language :: Python :: 3.4
Classifier: Programming Language :: Python :: 3.5
